docs/conf.py
tempdataset/__init__.py
tempdataset/__main__.py
tempdataset/cli.py
tempdataset/core/__init__.py
tempdataset/core/exceptions.py
tempdataset/core/generator.py
tempdataset/core/datasets/__init__.py
tempdataset/core/datasets/accounting.py
tempdataset/core/datasets/api_calls.py
tempdataset/core/datasets/app_usage.py
tempdataset/core/datasets/appointments.py
tempdataset/core/datasets/banking.py
tempdataset/core/datasets/base.py
tempdataset/core/datasets/clinical_trials.py
tempdataset/core/datasets/crm.py
tempdataset/core/datasets/cryptocurrency.py
tempdataset/core/datasets/customers.py
tempdataset/core/datasets/ecommerce.py
tempdataset/core/datasets/employees.py
tempdataset/core/datasets/energy.py
tempdataset/core/datasets/environmental.py
tempdataset/core/datasets/error_logs.py
tempdataset/core/datasets/industrial.py
tempdataset/core/datasets/insurance.py
tempdataset/core/datasets/inventory.py
tempdataset/core/datasets/investments.py
tempdataset/core/datasets/lab_results.py
tempdataset/core/datasets/loans.py
tempdataset/core/datasets/marketing.py
tempdataset/core/datasets/medical_history.py
tempdataset/core/datasets/patients.py
tempdataset/core/datasets/payments.py
tempdataset/core/datasets/performance.py
tempdataset/core/datasets/prescriptions.py
tempdataset/core/datasets/retail.py
tempdataset/core/datasets/reviews.py
tempdataset/core/datasets/sales.py
tempdataset/core/datasets/server_metrics.py
tempdataset/core/datasets/smarthome.py
tempdataset/core/datasets/social_media.py
tempdataset/core/datasets/stocks.py
tempdataset/core/datasets/suppliers.py
tempdataset/core/datasets/system_logs.py
tempdataset/core/datasets/traffic.py
tempdataset/core/datasets/user_profiles.py
tempdataset/core/datasets/user_sessions.py
tempdataset/core/datasets/weather.py
tempdataset/core/datasets/web_analytics.py
tempdataset/core/io/__init__.py
tempdataset/core/io/csv_handler.py
tempdataset/core/io/json_handler.py
tempdataset/core/utils/__init__.py
tempdataset-0.2.0.dist-info/licenses/LICENSE
tempdataset-0.2.0.dist-info/METADATA
tempdataset-0.2.0.dist-info/WHEEL
tempdataset-0.2.0.dist-info/entry_points.txt
tempdataset-0.2.0.dist-info/top_level.txt
tempdataset-0.2.0.dist-info/RECORD
