Metadata-Version: 2.4
Name: tempdataset
Version: 0.2.0
Summary: A lightweight Python library for generating realistic temporary datasets
Author-email: TempDataset Contributors <saqibshaikhdz@gmail.com>
License: MIT License
Project-URL: Homepage, https://github.com/dot-css/TempDataset
Project-URL: Documentation, https://tempdataset.readthedocs.io/
Project-URL: Repository, https://github.com/dot-css/TempDataset
Project-URL: Bug Tracker, https://github.com/dot-css/TempDataset/issues
Keywords: dataset,testing,development,sample-data,mock-data,csv,json,sales-data,temporary,lightweight
Classifier: Development Status :: 4 - Beta
Classifier: Intended Audience :: Developers
Classifier: Operating System :: OS Independent
Classifier: Programming Language :: Python :: 3
Classifier: Programming Language :: Python :: 3.7
Classifier: Programming Language :: Python :: 3.8
Classifier: Programming Language :: Python :: 3.9
Classifier: Programming Language :: Python :: 3.10
Classifier: Programming Language :: Python :: 3.11
Classifier: Programming Language :: Python :: 3.12
Classifier: Topic :: Software Development :: Libraries :: Python Modules
Classifier: Topic :: Software Development :: Testing
Classifier: Topic :: Utilities
Requires-Python: >=3.7
License-File: LICENSE
Provides-Extra: faker
Requires-Dist: faker>=18.0.0; extra == "faker"
Provides-Extra: dev
Requires-Dist: pytest>=7.0.0; extra == "dev"
Requires-Dist: pytest-cov>=4.0.0; extra == "dev"
Requires-Dist: pytest-benchmark>=4.0.0; extra == "dev"
Requires-Dist: memory-profiler>=0.60.0; extra == "dev"
Requires-Dist: psutil>=5.9.0; extra == "dev"
Requires-Dist: black>=22.0.0; extra == "dev"
Requires-Dist: flake8>=5.0.0; extra == "dev"
Requires-Dist: mypy>=1.0.0; extra == "dev"
Provides-Extra: test
Requires-Dist: pytest>=7.0.0; extra == "test"
Requires-Dist: pytest-cov>=4.0.0; extra == "test"
Requires-Dist: pytest-benchmark>=4.0.0; extra == "test"
Requires-Dist: memory-profiler>=0.60.0; extra == "test"
Requires-Dist: psutil>=5.9.0; extra == "test"
Provides-Extra: performance
Requires-Dist: memory-profiler>=0.60.0; extra == "performance"
Requires-Dist: psutil>=5.9.0; extra == "performance"
Requires-Dist: pytest-benchmark>=4.0.0; extra == "performance"
Dynamic: license-file
